slune/__init__.py
slune/base.py
slune/loggers.py
slune/savers.py
slune/searchers.py
slune/slune.py
slune/utils.py
slune_lib-0.0.11.dist-info/LICENSE
slune_lib-0.0.11.dist-info/METADATA
slune_lib-0.0.11.dist-info/WHEEL
slune_lib-0.0.11.dist-info/top_level.txt
slune_lib-0.0.11.dist-info/RECORD
