Metadata-Version: 2.1
Name: slune-lib
Version: 0.0.11
Summary: A package for performing hyperparameter tuning with the SLURM scheduling system.
Home-page: https://github.com/h-aze/slune
Author: Henry Bourne
Author-email: hwbourne@gmail.com
License: MIT
Platform: UNKNOWN
Requires-Python: >=3.8
Requires-Dist: pandas
